pydecentscale
