Metadata-Version: 1.0
Name: pydecentscale
Version: 0.3.1
Summary: A Python module to interact with the Decent Scale via bluetooth (BLE)
Home-page: https://github.com/lucapinello/pydecentscale
Author: Luca Pinello
Author-email: UNKNOWN
License: GPLv3
Platform: UNKNOWN
